allonias3/__init__.py
allonias3/base_path.py
allonias3/boto/__init__.py
allonias3/boto/boto_path.py
allonias3/configs.py
allonias3/encoder_decoder/__init__.py
allonias3/encoder_decoder/advanced.py
allonias3/encoder_decoder/basic.py
allonias3/helpers/__init__.py
allonias3/helpers/class_property.py
allonias3/helpers/enums.py
allonias3/helpers/getattr_safe_property.py
allonias3/helpers/nblog.py
allonias3/helpers/responses.py
allonias3/helpers/utils.py
allonias3/minio/__init__.py
allonias3/minio/helpers.py
allonias3/minio/minio_path.py
allonias3/s3_path.py
allonias3-1.9.0.dist-info/METADATA
allonias3-1.9.0.dist-info/WHEEL
allonias3-1.9.0.dist-info/RECORD
