Metadata-Version: 2.1
Name: allonias3
Version: 1.9.0
Summary: Class to interact with S3 in a similar fashion as pathlib.Path
Author: ALLONIA
Requires-Python: >=3.9,<4.0
Classifier: Programming Language :: Python :: 3
Classifier: Programming Language :: Python :: 3.9
Classifier: Programming Language :: Python :: 3.10
Classifier: Programming Language :: Python :: 3.11
Classifier: Programming Language :: Python :: 3.12
Provides-Extra: boto
Provides-Extra: datatypehandler
Requires-Dist: alloniaconfigs (>=1.1.2,<2.0.0)
Requires-Dist: boto3 (>=1.35.14,<2.0.0) ; extra == "boto"
Requires-Dist: botocore (>=1.35.14,<2.0.0) ; extra == "boto"
Requires-Dist: cloudpickle (>=3.0.0,<4.0.0)
Requires-Dist: dill (>=0.3.8,<0.4.0)
Requires-Dist: eval-type-backport (>=0.2.2,<0.3.0)
Requires-Dist: h5py (>=3.11.0,<4.0.0) ; extra == "datatypehandler"
Requires-Dist: hdf5plugin (>=5.0.0,<6.0.0) ; extra == "datatypehandler"
Requires-Dist: minio (>=7.2.8,<8.0.0)
Requires-Dist: odfpy (>=1.4.1,<2.0.0) ; extra == "datatypehandler"
Requires-Dist: openpyxl (>=3.1.5,<4.0.0) ; extra == "datatypehandler"
Requires-Dist: pandas (>=2.2.2,<3.0.0) ; extra == "datatypehandler"
Requires-Dist: pyarrow (>=17.0.0,<18.0.0) ; extra == "datatypehandler"
Requires-Dist: pydantic (>=2.9.1,<3.0.0)
Requires-Dist: python-dateutil (>=2.8.2,<3.0.0)
Requires-Dist: python-dotenv (>=1.0.1,<2.0.0)
Requires-Dist: pyxlsb (>=1.0.10,<2.0.0) ; extra == "datatypehandler"
Requires-Dist: tqdm (>=4.66.5,<5.0.0)
Requires-Dist: typeguard (>=4.3.0,<5.0.0)
Requires-Dist: xlrd (>=2.0.1,<3.0.0) ; extra == "datatypehandler"
